ntfsdump/__init__.py
ntfsdump/models/ImageFile.py
ntfsdump/models/Log.py
ntfsdump/models/MetaData.py
ntfsdump/models/NtfsFile.py
ntfsdump/models/NtfsVolume.py
ntfsdump/presenters/NtfsDumpPresenter.py
ntfsdump/views/BaseView.py
ntfsdump/views/NtfsDumpView.py
ntfsdump-2.5.3.dist-info/LICENSE
ntfsdump-2.5.3.dist-info/LICENSE.LESSER
ntfsdump-2.5.3.dist-info/METADATA
ntfsdump-2.5.3.dist-info/WHEEL
ntfsdump-2.5.3.dist-info/entry_points.txt
ntfsdump-2.5.3.dist-info/RECORD
