Metadata-Version: 2.1
Name: ntfsdump
Version: 2.5.3
Summary: An efficient tool for extracting files, directories, and alternate data streams directly from NTFS image files.
Home-page: https://github.com/sumeshi/ntfsdump
License: LGPLv3+
Keywords: Security,Forensics,DFIR,Windows,NTFS
Author: sumeshi
Author-email: sum3sh1@protonmail.com
Requires-Python: >=3.11,<4.0
Classifier: License :: Other/Proprietary License
Classifier: Programming Language :: Python :: 3
Classifier: Programming Language :: Python :: 3.11
Classifier: Programming Language :: Python :: 3.12
Requires-Dist: libewf-python (>=20230212,<20230213)
Requires-Dist: libvhdi-python (>=20221124,<20221125)
Requires-Dist: libvmdk-python (>=20221124,<20221125)
Requires-Dist: poetry (>=1.7.0,<2.0.0)
Requires-Dist: pytest (>=7.4.3,<8.0.0)
Requires-Dist: pytsk3 (>=20231007,<20231008)
Project-URL: Repository, https://github.com/sumeshi/ntfsdump
